sgspy/__init__.py
sgspy/_sgs.cpython-312-x86_64-linux-gnu.so
sgspy/calculate/__init__.py
sgspy/calculate/pca/__init__.py
sgspy/calculate/pca/pca.py
sgspy/calculate/representation/__init__.py
sgspy/calculate/representation/representation.py
sgspy/sample/__init__.py
sgspy/sample/ahels/__init__.py
sgspy/sample/ahels/ahels.py
sgspy/sample/clhs/__init__.py
sgspy/sample/clhs/clhs.py
sgspy/sample/nc/__init__.py
sgspy/sample/nc/nc.py
sgspy/sample/srs/__init__.py
sgspy/sample/srs/srs.py
sgspy/sample/strat/__init__.py
sgspy/sample/strat/strat.py
sgspy/sample/systematic/__init__.py
sgspy/sample/systematic/systematic.py
sgspy/stratify/__init__.py
sgspy/stratify/breaks/__init__.py
sgspy/stratify/breaks/breaks.py
sgspy/stratify/kmeans/__init__.py
sgspy/stratify/kmeans/kmeans.py
sgspy/stratify/map/__init__.py
sgspy/stratify/map/map_stratifications.py
sgspy/stratify/poly/__init__.py
sgspy/stratify/poly/poly.py
sgspy/stratify/quantiles/__init__.py
sgspy/stratify/quantiles/quantiles.py
sgspy/utils/__init__.py
sgspy/utils/plot.py
sgspy/utils/raster.py
sgspy/utils/vector.py
sgspy-1.0.1.data/data/sgspy/libonedal.so.3
sgspy-1.0.1.data/data/sgspy/proj.db
sgspy-1.0.1.dist-info/METADATA
sgspy-1.0.1.dist-info/WHEEL
sgspy-1.0.1.dist-info/RECORD
