Metadata-Version: 2.1
Name: sgspy
Version: 1.0.1
Requires-Dist: numpy
Requires-Dist: matplotlib
Requires-Dist: daal==2025.9.0
Requires-Dist: tbb==2022.*
Requires-Dist: mkl==2025.3.0
Requires-Dist: onemkl-license==2025.3.0
Provides-Extra: test
Requires-Dist: pytest; extra == "test"
Requires-Dist: geopandas; extra == "test"
